AM_PlusOne/__init__.py
AM_PlusOne/plus_one.py
AM_GH_PlusOne-0.0.1.dist-info/LICENSE
AM_GH_PlusOne-0.0.1.dist-info/METADATA
AM_GH_PlusOne-0.0.1.dist-info/WHEEL
AM_GH_PlusOne-0.0.1.dist-info/top_level.txt
AM_GH_PlusOne-0.0.1.dist-info/RECORD
