Metadata-Version: 2.1
Name: AM-GH-PlusOne
Version: 0.0.1
Summary: my first pip package
Author: Amine Gharout
Classifier: Programming Language :: Python :: 3
Classifier: License :: OSI Approved :: MIT License
Classifier: Operating System :: OS Independent
Requires-Python: >=3.6
License-File: LICENSE
